<annotation>
	<folder>angry</folder>
	<filename>angry (410).jpg</filename>
	<path>/Users/aprzybycien/Documents/psy/data/angry/angry (410).jpg</path>
	<source>
		<database>Unknown</database>
	</source>
	<size>
		<width>491</width>
		<height>491</height>
		<depth>3</depth>
	</size>
	<segmented>0</segmented>
	<object>
		<name>dog</name>
		<pose>Unspecified</pose>
		<truncated>1</truncated>
		<difficult>0</difficult>
		<bndbox>
			<xmin>41</xmin>
			<ymin>1</ymin>
			<xmax>491</xmax>
			<ymax>412</ymax>
		</bndbox>
	</object>
</annotation>
